calculators/__init__.py
calculators/audio/__init__.py
calculators/audio/mfcc_mel_calculators_pb2.py
calculators/audio/rational_factor_resample_calculator_pb2.py
calculators/audio/spectrogram_calculator_pb2.py
calculators/audio/stabilized_log_calculator_pb2.py
calculators/audio/time_series_framer_calculator_pb2.py
calculators/core/__init__.py
calculators/core/bypass_calculator_pb2.py
calculators/core/clip_vector_size_calculator_pb2.py
calculators/core/concatenate_vector_calculator_pb2.py
calculators/core/constant_side_packet_calculator_pb2.py
calculators/core/dequantize_byte_array_calculator_pb2.py
calculators/core/flow_limiter_calculator_pb2.py
calculators/core/gate_calculator_pb2.py
calculators/core/get_vector_item_calculator_pb2.py
calculators/core/graph_profile_calculator_pb2.py
calculators/core/packet_cloner_calculator_pb2.py
calculators/core/packet_resampler_calculator_pb2.py
calculators/core/packet_thinner_calculator_pb2.py
calculators/core/quantize_float_vector_calculator_pb2.py
calculators/core/sequence_shift_calculator_pb2.py
calculators/core/split_vector_calculator_pb2.py
calculators/image/__init__.py
calculators/image/bilateral_filter_calculator_pb2.py
calculators/image/feature_detector_calculator_pb2.py
calculators/image/image_clone_calculator_pb2.py
calculators/image/image_cropping_calculator_pb2.py
calculators/image/image_transformation_calculator_pb2.py
calculators/image/mask_overlay_calculator_pb2.py
calculators/image/opencv_encoded_image_to_image_frame_calculator_pb2.py
calculators/image/opencv_image_encoder_calculator_pb2.py
calculators/image/recolor_calculator_pb2.py
calculators/image/rotation_mode_pb2.py
calculators/image/scale_image_calculator_pb2.py
calculators/image/segmentation_smoothing_calculator_pb2.py
calculators/image/set_alpha_calculator_pb2.py
calculators/image/warp_affine_calculator_pb2.py
calculators/internal/__init__.py
calculators/internal/callback_packet_calculator_pb2.py
calculators/tensor/__init__.py
mediasolutions-0.0.7.dist-info/METADATA
mediasolutions-0.0.7.dist-info/WHEEL
mediasolutions-0.0.7.dist-info/top_level.txt
mediasolutions-0.0.7.dist-info/RECORD
