Metadata-Version: 2.1
Name: mediasolutions
Version: 0.0.7
Summary: A ML Library
Home-page: UNKNOWN
Author: Jaswanth
Author-email: jaswanthmadiya@gmail.com
License: UNKNOWN
Keywords: python,mediapipe
Platform: UNKNOWN
Classifier: Development Status :: 1 - Planning
Classifier: Intended Audience :: Developers
Classifier: Programming Language :: Python :: 3
Classifier: Operating System :: Unix
Classifier: Operating System :: MacOS :: MacOS X
Classifier: Operating System :: Microsoft :: Windows
Requires-Dist: opencv-python
Requires-Dist: pyautogui
